nonebot_plugin_jmdownload/__init__.py
nonebot_plugin_jmdownload/config.py
nonebot_plugin_jmdownload/download.py
nonebot_plugin_jmdownload/handlers.py
nonebot_plugin_jmdownload/pdf_converter.py
nonebot_plugin_jmdownload/utils.py
nonebot_plugin_jmdownload-1.4.0.dist-info/LICENSE
nonebot_plugin_jmdownload-1.4.0.dist-info/METADATA
nonebot_plugin_jmdownload-1.4.0.dist-info/WHEEL
nonebot_plugin_jmdownload-1.4.0.dist-info/top_level.txt
nonebot_plugin_jmdownload-1.4.0.dist-info/RECORD
