Metadata-Version: 2.2
Name: nonebot_plugin_jmdownload
Version: 1.4.0
Summary: 基于NoneBot2的JM漫画下载插件
Home-page: https://github.com/QuickLAW/nonebot_plugin_JMDownload
Author: QuickLAW
Author-email: yewillwork@outlook.com
License: BSD 3-Clause License
Platform: all
Classifier: Development Status :: 4 - Beta
Classifier: Operating System :: OS Independent
Classifier: License :: OSI Approved :: BSD License
Classifier: Programming Language :: Python :: 3
Classifier: Programming Language :: Python :: 3.8
Classifier: Programming Language :: Python :: 3.9
Classifier: Programming Language :: Python :: 3.10
Classifier: Programming Language :: Python :: 3.11
Classifier: Topic :: Internet :: WWW/HTTP
Classifier: Topic :: Software Development :: Libraries :: Python Modules
License-File: LICENSE
Requires-Dist: nonebot2>=2.0.0rc1
Requires-Dist: nonebot-adapter-onebot>=2.0.0
Requires-Dist: jmcomic
Requires-Dist: PyYAML
Requires-Dist: Pillow
Requires-Dist: reportlab
Requires-Dist: psutil
Requires-Dist: PyPDF2
Dynamic: author
Dynamic: author-email
Dynamic: classifier
Dynamic: description
Dynamic: description-content-type
Dynamic: home-page
Dynamic: license
Dynamic: platform
Dynamic: requires-dist
Dynamic: summary
